signed_backbones.py
signed_backbones-0.91.3.dist-info/WHEEL
signed_backbones-0.91.3.dist-info/METADATA
signed_backbones-0.91.3.dist-info/RECORD
