Metadata-Version: 2.1
Name: signed_backbones
Version: 0.91.3
Summary: Python package for extracting signed backbones of intrinsically dense weighted networks.
Home-page: https://github.com/furkangursoy/signed_backbones
License: UNKNOWN
Author: Furkan Gürsoy
Author-email: furkan.gursoy@boun.edu.tr
Classifier: License :: OSI Approved :: MIT License
